PyPop/_EWSlatkinExact.pypy38-pp73-win_amd64.pyd
PyPop/_Emhaplofreq.pypy38-pp73-win_amd64.pyd
PyPop/_Gthwe.pypy38-pp73-win_amd64.pyd
PyPop/_Haplostats.pypy38-pp73-win_amd64.pyd
PyPop/_Pvalue.pypy38-pp73-win_amd64.pyd
PyPop/__init__.py
PyPop/_deprecations.py
PyPop/_metadata.py
PyPop/_version.py
PyPop/arlequin.py
PyPop/citation.py
PyPop/command_line_interface.py
PyPop/datatypes.py
PyPop/filters.py
PyPop/haplo.py
PyPop/hardyweinberg.py
PyPop/homozygosity.py
PyPop/parsers.py
PyPop/popaggregate.py
PyPop/popanalysis.py
PyPop/popmeta.py
PyPop/pypop.py
PyPop/randombinning.py
PyPop/utils.py
PyPop/citation/CITATION.apalike
PyPop/citation/CITATION.bibtex
PyPop/citation/CITATION.cff
PyPop/citation/CITATION.codemeta
PyPop/citation/CITATION.endnote
PyPop/citation/CITATION.ris
PyPop/citation/CITATION.schema.org
PyPop/citation/CITATION.zenodo
PyPop/xslt/__init__.py
PyPop/xslt/allelelist-by-locus.xsl
PyPop/xslt/common.xsl
PyPop/xslt/emhaplofreq.xsl
PyPop/xslt/filter.xsl
PyPop/xslt/haplolist-by-group.xsl
PyPop/xslt/hardyweinberg.xsl
PyPop/xslt/homozygosity.xsl
PyPop/xslt/html.xsl
PyPop/xslt/lib.xsl
PyPop/xslt/meta-to-tsv.xsl
PyPop/xslt/phylip-allele.xsl
PyPop/xslt/phylip-haplo.xsl
PyPop/xslt/sort-by-locus.xsl
PyPop/xslt/summary.xsl
PyPop/xslt/text.xsl
pypop_genomics-1.4.0.dist-info/AUTHORS.rst
pypop_genomics-1.4.0.dist-info/LICENSE
pypop_genomics-1.4.0.dist-info/METADATA
pypop_genomics-1.4.0.dist-info/WHEEL
pypop_genomics-1.4.0.dist-info/entry_points.txt
pypop_genomics-1.4.0.dist-info/top_level.txt
pypop_genomics-1.4.0.dist-info/RECORD
