Metadata-Version: 2.1
Name: pypop-genomics
Version: 1.4.0
Summary: PyPop: Python for Population Genomics
Author: Alex Lancaster
Maintainer: PyPop team
License: GPL-2.0-or-later
Project-URL: Homepage, http://pypop.org/
Project-URL: Documentation, http://pypop.org/docs/
Project-URL: Changelog, https://github.com/alexlancaster/pypop/blob/main/NEWS.md
Project-URL: Source, https://github.com/alexlancaster/pypop/
Project-URL: Tracker, https://github.com/alexlancaster/pypop/issues
Keywords: bioinformatics,population-genomics,evolutionary-biology,population-genetics
Classifier: Programming Language :: Python :: 3
Classifier: Intended Audience :: Science/Research
Classifier: Topic :: Scientific/Engineering :: Bio-Informatics
Classifier: Operating System :: MacOS :: MacOS X
Classifier: Operating System :: Microsoft :: Windows
Classifier: Operating System :: POSIX :: Linux
License-File: LICENSE
License-File: AUTHORS.rst
Requires-Dist: numpy <=2.4.1
Requires-Dist: lxml <=6.0.2
Requires-Dist: pooch <=v1.8.2
Requires-Dist: importlib-resources ; python_version <= "3.8"
Requires-Dist: importlib-metadata ; python_version <= "3.8"
Provides-Extra: test
Requires-Dist: pytest ; extra == 'test'
Requires-Dist: pytest-benchmark[histogram] ; extra == 'test'
Requires-Dist: pytest-doctestplus ; extra == 'test'
Provides-Extra: test-pval-benchmarking
Requires-Dist: scipy ; extra == 'test-pval-benchmarking'
Requires-Dist: sphinx ; (platform_python_implementation != "PyPy") and extra == 'test'
